praw_codials/__init__.py
praw_codials/parsing.py
praw_codials/scraping_tools.py
praw_codials/storage_classes.py
praw_codials-1.0.4.data/scripts/praw-codials
praw_codials-1.0.4.dist-info/LICENSE
praw_codials-1.0.4.dist-info/METADATA
praw_codials-1.0.4.dist-info/WHEEL
praw_codials-1.0.4.dist-info/top_level.txt
praw_codials-1.0.4.dist-info/RECORD
