Metadata-Version: 2.1
Name: praw-codials
Version: 1.0.4
Summary: PRAW-Powered COmmunity & DomaIn tArgeted Link Scraper
Home-page: https://github.com/nkuehnle/praw-codials
Author: Neil Kuehnle
Author-email: nkuehnle1191@gmail.com
License: MIT
Keywords: reddit,webscraper,command-line
Platform: UNKNOWN
Classifier: Development Status :: 5 - Production/Stable
Classifier: Environment :: Console
Classifier: Intended Audience :: Developers
Classifier: Intended Audience :: Science/Research
Classifier: License :: OSI Approved :: MIT License
Classifier: Natural Language :: English
Classifier: Operating System :: OS Independent
Classifier: Programming Language :: Python
Classifier: Programming Language :: Python :: 3 :: Only
Classifier: Topic :: Adaptive Technologies
Requires-Python: ~=3.6 
License-File: LICENSE
Requires-Dist: praw
Requires-Dist: pandas
Requires-Dist: pyaml
